setup.py
python/locale_simple.py
python/locale_simple.egg-info/PKG-INFO
python/locale_simple.egg-info/SOURCES.txt
python/locale_simple.egg-info/dependency_links.txt
python/locale_simple.egg-info/top_level.txt