Metadata-Version: 1.0
Name: locale-simple
Version: 0.014
Summary: Python verrsion of Locale::Simple, Translation system based on gettext storage, same API in Perl and Javascript
Home-page: https://github.com/Getty/p5-locale-simple/
Author: Michael Smith
Author-email: crazedpsyc@duckduckgo.com
License: PerlArtistic
Platform: any
Classifier: Development Status :: 4 - Beta
Classifier: Intended Audience :: Developers
Classifier: Operating System :: OS Independent
Classifier: Programming Language :: Python
Classifier: Topic :: Software Development :: Localization
